[
	{
		"name": "咪嚕",
		"breed": "博美",
		"type": "狗",
		"gender": "公",
		"shape": "小型",
		"color": "棕色",
		"age": "老年",
		"fixed": "已結紮",
		"location": "新北市 新莊區",
		"contact": "琳琳",
		"phone": "0903091368",
		"place": "[object Object]",
		"image": "https://a8c1cd483071.ngrok.io/Animal/dog/9.jpg",
		"date": "2021/5/24"
	},
	{
		"breed": "臘腸狗",
		"date": "2021/5/24"
	},
	{
		"name": "多比",
		"breed": "臘腸狗",
		"type": "狗",
		"gender": "公",
		"shape": "小型",
		"color": "棕色",
		"age": "老年",
		"fixed": "已結紮",
		"location": "台北市 大安區",
		"contact": "黃筱芸",
		"phone": "0937629290",
		"place": "[object Object]",
		"image": "https://a8c1cd483071.ngrok.io/Animal/dog/0.jpg",
		"date": "2021/5/24"
	},
	{
		"name": "多多",
		"breed": "臘腸狗",
		"type": "狗",
		"gender": "公",
		"shape": "小型",
		"color": "黑色",
		"age": "成年",
		"fixed": "未結紮",
		"location": "桃園市 中壢區",
		"contact": "豬小文",
		"phone": "0901285073",
		"place": "[object Object]",
		"image": "https://a8c1cd483071.ngrok.io/Animal/dog/13.jpg",
		"date": "2021/5/24"
	},
	{
		"name": "Maru",
		"breed": "臘腸狗",
		"type": "狗",
		"gender": "母",
		"shape": "小型",
		"color": "黑色",
		"age": "老年",
		"fixed": "已結紮",
		"location": "苗栗縣 頭份市",
		"contact": "林姵希",
		"phone": "0983115088",
		"place": "[object Object]",
		"image": "https://a8c1cd483071.ngrok.io/Animal/dog/29.jpg",
		"date": "2021/5/24"
	},
	{
		"name": "Lala",
		"breed": "臘腸狗",
		"type": "狗",
		"gender": "母",
		"shape": "小型",
		"color": "茶色",
		"age": "成年",
		"fixed": "未結紮",
		"location": "台中市 梧棲區",
		"contact": "陳沛慈",
		"phone": "0953363357",
		"place": "[object Object]",
		"image": "https://a8c1cd483071.ngrok.io/Animal/dog/81.jpg",
		"date": "2021/5/24"
	}
]